CHANGELOG.md
LICENSE
MANIFEST.in
README.md
setup.cfg
setup.py
sgp30_exporter/app.py
sgp30_exporter/main.py
sgp30_exporter/sgp30_source.py
sgp30_exporter.egg-info/PKG-INFO
sgp30_exporter.egg-info/SOURCES.txt
sgp30_exporter.egg-info/dependency_links.txt
sgp30_exporter.egg-info/entry_points.txt
sgp30_exporter.egg-info/requires.txt
sgp30_exporter.egg-info/top_level.txt
test/__init__.py
test/test_app.py
test/test_main.py
test/test_sgp30_source.py