Metadata-Version: 2.1
Name: sgp30-exporter
Version: 0.2.1
Summary: UNKNOWN
Home-page: https://github.com/urbas/sgp30-exporter
Author: Matej Urbas
Author-email: matej.urbas@gmail.com
License: MIT license
Keywords: sgp30-exporter,air quality,prometheus,exporter
Platform: UNKNOWN
License-File: LICENSE
